{
    "name": "PAL-8 Light",
    "tokenColors": [
        {
            "name": "Comment",
            "scope": "comment",
            "settings": {
                "foreground": "#008000"
            }
        },
        {
            "name": "Constant",
            "scope": "constant",
            "settings": {
                "foreground": "#098658"
            }
        },
        {
            "name": "Label",
            "scope": "entity.name.label",
            "settings": {
                "foreground": "#0000ff"
            }
        },
        {
            "name": "Parameter",
            "scope": "entity.name.parameter",
            "settings": {
                "foreground": "#8a1bff"
            }
        },
        {
            "name": "Value",
            "scope": "entity.name.value",
            "settings": {
                "foreground": "#a31515"
            }
        },
        {
            "name": "Variable Label",
            "scope": "entity.name.variable",
            "settings": {
                "foreground": "#0000ff"
            }
        },
        {
            "name": "String",
            "scope": "entity.other.string",
            "settings": {
                "foreground": "#7dc0a8"
            }
        },
        {
            "name": "TerminatePass",
            "scope": "keyword.control.endofpass",
            "settings": {
                "foreground": "#ff0000"
            }
        },
        {
            "name": "Memory Location",
            "scope": "keyword.control.location",
            "settings": {
                "foreground": "#80c0d0",
                "fontStyle": "bold"
            }
        },
        {
            "name": "Memory Contents",
            "scope": "keyword.control.memory",
            "settings": {
                "foreground": "#80c0d0",
                "fontStyle": "bold"
            }
        },
        {
            "name": "Pseudo Operation",
            "scope": "keyword.control.pseudo",
            "settings": {
                "foreground": "#80c0d0",
                "fontStyle": "bold"
            }
        },
        {
            "name": "Keyword Storage",
            "scope": "keyword.control.storage",
            "settings": {
                "foreground": "#a0a080"
            }
        },
        {
            "name": "Instruction",
            "scope": "keyword.operator.instruction",
            "settings": {
                "foreground": "#74531f"
            }
        }
    ]
}
